COPYING
MANIFEST.in
NEWS
README
setup.py
examples/demo.py
lib/pytaf/__init__.py
lib/pytaf/taf.py
lib/pytaf/tafdecoder.py
lib/pytaf.egg-info/PKG-INFO
lib/pytaf.egg-info/SOURCES.txt
lib/pytaf.egg-info/dependency_links.txt
lib/pytaf.egg-info/top_level.txt
lib/pytaf.egg-info/zip-safe