Metadata-Version: 1.1
Name: pytaf
Version: 1.1.1
Summary: TAF (Terminal Aerodrome Forecast) parser and decoder
Home-page: http://github.com/dmbaturin/pytaf
Author: Daniil Baturin
Author-email: daniil@baturin.org
License: MIT
Keywords: aviation weather meteorology taf
Platform: UNKNOWN
Classifier: Development Status :: 5 - Production/Stable
Classifier: License :: OSI Approved :: MIT License
Classifier: Operating System :: OS Independent
Classifier: Programming Language :: Python :: 2.6
Classifier: Programming Language :: Python :: 2.7
Classifier: Programming Language :: Python :: 3
Classifier: Topic :: Scientific/Engineering
